lummao/__init__.py
lummao/_compiler.pyd
lummao/cli.py
lummao/exceptions.py
lummao/goto.py
lummao/http.py
lummao/lslexecutils.py
lummao/shellsl.py
lummao/vendor/__init__.py
lummao/vendor/lslopt/__init__.py
lummao/vendor/lslopt/lslbasefuncs.py
lummao/vendor/lslopt/lslcommon.py
lummao/vendor/lslopt/lslextrafuncs.py
lummao/vendor/lslopt/lslfuncs.py
lummao/vendor/lslopt/lsljson.py
lummao/vendor/lslopt/strutil.py
lummao-0.5.2.dist-info/LICENSE
lummao-0.5.2.dist-info/METADATA
lummao-0.5.2.dist-info/WHEEL
lummao-0.5.2.dist-info/entry_points.txt
lummao-0.5.2.dist-info/top_level.txt
lummao-0.5.2.dist-info/RECORD
