Metadata-Version: 2.1
Name: lummao
Version: 0.5.2
Summary: Toolkit for compiling and executing the Linden Scripting Language as Python
Home-page: https://github.com/SaladDais/Lummao
Author: Salad Dais
Author-email: SaladDais@users.noreply.github.com
License: GPLv3
Requires-Python: >=3.8
License-File: LICENSE
Requires-Dist: bytecode <1.0,>=0.14
Requires-Dist: aiohttp <4.0,>=3.6
